kobacktranslation/__init__.py
kobacktranslation-0.0.0.dist-info/LICENSE
kobacktranslation-0.0.0.dist-info/METADATA
kobacktranslation-0.0.0.dist-info/WHEEL
kobacktranslation-0.0.0.dist-info/top_level.txt
kobacktranslation-0.0.0.dist-info/RECORD
