Metadata-Version: 2.1
Name: kobacktranslation
Version: 0.0.0
Summary: Korean Back-Translation Package
Home-page: https://github.com/toriving/KoBackTranslation
Author: Dongju.Park
Author-email: toriving@gmail.com
License: MIT
Keywords: NLP deep learning kobacktranslation korean backtranslation translation machine translation
Platform: UNKNOWN
Classifier: Development Status :: 5 - Production/Stable
Classifier: Intended Audience :: Developers
Classifier: Intended Audience :: Education
Classifier: Intended Audience :: Science/Research
Classifier: License :: OSI Approved :: MIT License
Classifier: Operating System :: OS Independent
Classifier: Programming Language :: Python :: 3
Classifier: Programming Language :: Python :: 3.6
Classifier: Programming Language :: Python :: 3.7
Classifier: Programming Language :: Python :: 3.8
Classifier: Programming Language :: Python :: 3.9
Classifier: Topic :: Scientific/Engineering :: Artificial Intelligence
Requires-Python: >=3.6.0
License-File: LICENSE
